{
  "updatedAt": "2026-07-20T19:35:41",
  "now": {
    "artist": "Blood Orange",
    "title": "Mind Loaded  feat. Caroline Polachek  Lorde & Mustafa",
    "album": "Essex Honey • 2025",
    "category": "AUDIO"
  },
  "comingUp": [
    {
      "time": "7:39 pm",
      "artist": "Beck",
      "title": "Country Down"
    },
    {
      "time": "7:43 pm",
      "artist": "Aldous Harding",
      "title": "Venus in the Zinnia feat. H. Hawkline"
    },
    {
      "time": "7:46 pm",
      "artist": "Arctic Monkeys",
      "title": "Don't Sit Down 'cause I've Moved Your Chair"
    },
    {
      "time": "7:49 pm",
      "artist": "Rolling Blackouts Coastal Fever",
      "title": "Cars in Space"
    }
  ],
  "recent": [
    {
      "time": "7:35 pm",
      "artist": "Blood Orange",
      "title": "Mind Loaded  feat. Caroline Polachek  Lorde & Mustafa",
      "album": "Essex Honey • 2025"
    },
    {
      "time": "7:32 pm",
      "artist": "Neon Indian",
      "title": "Ephemeral Artery",
      "album": "Psychic Chasms • 2010"
    },
    {
      "time": "7:30 pm",
      "artist": "Jack White",
      "title": "Dollar Bill",
      "album": "Frozen Charlotte • 2026"
    },
    {
      "time": "7:27 pm",
      "artist": "Son Little",
      "title": "In Orbit",
      "album": "Cityfolk • 2025"
    },
    {
      "time": "7:24 pm",
      "artist": "Bonny Doon",
      "title": "You Can't Stay the Same (Feat. Waxahatchee)",
      "album": "Let There Be Music • 2023"
    },
    {
      "time": "7:19 pm",
      "artist": "Wild Pink",
      "title": "Round Of Applause At The End Of The World",
      "album": "Still Coming Down • 2026"
    },
    {
      "time": "7:16 pm",
      "artist": "Alex G",
      "title": "Oranges",
      "album": "Headlights • 2025"
    },
    {
      "time": "7:12 pm",
      "artist": "Bolis Pupul",
      "title": "Completely Half",
      "album": "Letter To Yu • 2024"
    },
    {
      "time": "7:08 pm",
      "artist": "Kurt Vile",
      "title": "Shame Chamber",
      "album": "Wakin on a Pretty Daze • 2013"
    },
    {
      "time": "7:04 pm",
      "artist": "Widowspeak",
      "title": "If You Change",
      "album": "Roses • 2026"
    },
    {
      "time": "6:58 pm",
      "artist": "BODEGA",
      "title": "Tarkovski",
      "album": "Our Brand Could Be Yr Life • 2024"
    },
    {
      "time": "6:55 pm",
      "artist": "Cherry Glazerr",
      "title": "Ohio",
      "album": "Stuffed & Ready • 2019"
    },
    {
      "time": "6:51 pm",
      "artist": "The National",
      "title": "Guilty Party",
      "album": "Sleep Well Beast • 2017"
    },
    {
      "time": "6:47 pm",
      "artist": "Sigur Ros",
      "title": "Vio spilum endalaust  (We Play Endlessly)",
      "album": "Meo suo i eyrum vio spilum endalaust • 2008"
    },
    {
      "time": "6:44 pm",
      "artist": "Slow Pulp",
      "title": "Better Man",
      "album": "Melodie • 2026"
    },
    {
      "time": "6:38 pm",
      "artist": "Happy Mondays",
      "title": "Wrote for Luck",
      "album": "Bummed • 1988"
    },
    {
      "time": "6:35 pm",
      "artist": "Shannon and the Clams",
      "title": "My Man",
      "album": "Gone by the Dawn • 2015"
    },
    {
      "time": "6:32 pm",
      "artist": "Jay Som",
      "title": "1 Billion Dogs",
      "album": "Everybody Works • 2017"
    },
    {
      "time": "6:29 pm",
      "artist": "Turnstile",
      "title": "DON'T PLAY",
      "album": "GLOW ON • 2021"
    },
    {
      "time": "6:26 pm",
      "artist": "Sylvan Esso",
      "title": "The Glow",
      "album": "What Now • 2017"
    },
    {
      "time": "6:23 pm",
      "artist": "bar italia",
      "title": "changer",
      "album": "tracey denim • 2023"
    },
    {
      "time": "6:19 pm",
      "artist": "Rostam feat. Clairo",
      "title": "Hardy",
      "album": "American Stories • 2026"
    },
    {
      "time": "6:16 pm",
      "artist": "Cheekface",
      "title": "I Don't Work Here",
      "album": "Podium • 2026"
    },
    {
      "time": "6:13 pm",
      "artist": "beabadoobee",
      "title": "the way things go",
      "album": "• 2023"
    },
    {
      "time": "6:08 pm",
      "artist": "Broken Social Scene",
      "title": "Sweetest Kill",
      "album": "Forgiveness Rock Record • 2010"
    }
  ]
}