{
  "updatedAt": "2026-07-16T15:27:21",
  "now": {
    "artist": "Liner",
    "title": "Liner",
    "album": "",
    "category": "AUDIO"
  },
  "comingUp": [
    {
      "time": "3:27 pm",
      "artist": "The Byrds",
      "title": "I'll Feel a Whole Lot Better"
    },
    {
      "time": "3:30 pm",
      "artist": "Imagine Dragons",
      "title": "Radioactive"
    },
    {
      "time": "3:33 pm",
      "artist": "Ride",
      "title": "Leave Them All Behind"
    },
    {
      "time": "3:41 pm",
      "artist": "Sebadoh",
      "title": "On Fire"
    }
  ],
  "recent": [
    {
      "time": "3:21 pm",
      "artist": "Aesop Rock",
      "title": "None Shall Pass",
      "album": "None Shall Pass • 2007"
    },
    {
      "time": "3:18 pm",
      "artist": "Don Gibson",
      "title": "Oh Lonesome Me",
      "album": "Oh Lonesome Me • 1958"
    },
    {
      "time": "3:12 pm",
      "artist": "Oasis",
      "title": "Live Forever",
      "album": "Definitely Maybe • 1994"
    },
    {
      "time": "3:07 pm",
      "artist": "Fleetwood Mac",
      "title": "Not That Funny",
      "album": "Tusk • 1979"
    },
    {
      "time": "3:04 pm",
      "artist": "The Sonics",
      "title": "Strychnine",
      "album": "Here Are The Sonics!!! • 1965"
    },
    {
      "time": "3:02 pm",
      "artist": "Wire",
      "title": "Three Girl Rhumba",
      "album": "Pink Flag • 1977"
    },
    {
      "time": "2:59 pm",
      "artist": "The Doors",
      "title": "Hello, I Love You",
      "album": "Waiting for the Sun • 1968"
    },
    {
      "time": "2:48 pm",
      "artist": "The Doors",
      "title": "L.A. Woman",
      "album": "L.A. Woman • 1971"
    },
    {
      "time": "2:43 pm",
      "artist": "Panda Bear & Sonic Boom",
      "title": "Edge of the Edge",
      "album": "Edge of the Edge • 2022"
    },
    {
      "time": "2:36 pm",
      "artist": "Bruce Springsteen",
      "title": "The River",
      "album": "The River • 1980"
    },
    {
      "time": "2:31 pm",
      "artist": "T'Pau",
      "title": "Heart And Soul",
      "album": "Bridge of Spies • 1987"
    },
    {
      "time": "2:25 pm",
      "artist": "Nirvana",
      "title": "Drain You",
      "album": "Nevermind • 1991"
    },
    {
      "time": "2:18 pm",
      "artist": "Nirvana.",
      "title": "Smells Like Teen Spirit",
      "album": "Nevermind • 1991"
    },
    {
      "time": "2:14 pm",
      "artist": "Gorillaz",
      "title": "Andromeda feat. D.R.A.M.",
      "album": "Humanz • 2017"
    },
    {
      "time": "2:08 pm",
      "artist": "Black Eyed Peas",
      "title": "Let's Get It Started",
      "album": "Elephunk • 2004"
    },
    {
      "time": "2:01 pm",
      "artist": "Coldplay",
      "title": "The Scientist",
      "album": "A Rush of Blood to the Head • 2002"
    },
    {
      "time": "1:55 pm",
      "artist": "Leon Bridges",
      "title": "Beyond",
      "album": "Good Thing • 2018"
    },
    {
      "time": "1:52 pm",
      "artist": "Neutral Milk Hotel",
      "title": "The King of Carrot Flowers Pt. One",
      "album": "In The Aeroplane Over The Sea • 1998"
    },
    {
      "time": "1:46 pm",
      "artist": "Talking Heads",
      "title": "Psycho Killer",
      "album": "Talking Heads: 77 • 1977"
    },
    {
      "time": "1:43 pm",
      "artist": "The Beatles",
      "title": "Yesterday",
      "album": "Help! • 1965"
    },
    {
      "time": "1:37 pm",
      "artist": "Styx",
      "title": "Renegade",
      "album": "Pieces of Eight • 1979"
    },
    {
      "time": "1:35 pm",
      "artist": "The Beatles",
      "title": "I'm Happy Just To Dance With You",
      "album": "A Hard Day's Night • 1964"
    },
    {
      "time": "1:31 pm",
      "artist": "Sparks",
      "title": "Something for the Girl With Everything",
      "album": "Propaganda • 1974"
    },
    {
      "time": "1:27 pm",
      "artist": "Asuka Ito, Daisuke Matsuoka",
      "title": "Staff Credits ~From 'Tomodachi Life'~",
      "album": "Nintendo Music •"
    },
    {
      "time": "1:22 pm",
      "artist": "The Human League",
      "title": "Don't You Want Me",
      "album": "Dare • 1981"
    }
  ]
}